{"id":"542303","name":"Marcell Ozuna","team":null,"series":{"bref_war_batting":{"bwar":[["2026-06-30",-0.75]]},"savant_xstats_batter":{"ba":[["2026-06-30",0.204]],"bip":[["2026-06-30",138.0]],"est_ba":[["2026-06-30",0.228]],"est_ba_minus_ba_diff":[["2026-06-30",-0.024]],"est_slg":[["2026-06-30",0.417]],"est_slg_minus_slg_diff":[["2026-06-30",-0.0869999999999999]],"est_woba":[["2026-06-30",0.315]],"est_woba_minus_woba_diff":[["2026-06-30",-0.0389999999999999]],"pa":[["2026-06-30",229.0]],"slg":[["2026-06-30",0.33]],"woba":[["2026-06-30",0.276]]}}}