{"id":"606996","name":"Kyle Hart","team":null,"series":{"bref_war_pitching":{"bwar":[["2026-06-30",0.17]]},"savant_xstats_pitcher":{"ba":[["2026-06-30",0.189]],"bip":[["2026-06-30",73.0]],"era":[["2026-06-30",4.05]],"era_minus_xera_diff":[["2026-06-30",0.47]],"est_ba":[["2026-06-30",0.223]],"est_ba_minus_ba_diff":[["2026-06-30",-0.034]],"est_slg":[["2026-06-30",0.348]],"est_slg_minus_slg_diff":[["2026-06-30",-0.0479999999999999]],"est_woba":[["2026-06-30",0.296]],"est_woba_minus_woba_diff":[["2026-06-30",-0.0329999999999999]],"pa":[["2026-06-30",106.0]],"slg":[["2026-06-30",0.3]],"woba":[["2026-06-30",0.263]],"xera":[["2026-06-30",3.58]]}}}