{"id":"668964","name":"Tobias Myers","team":null,"series":{"bref_war_pitching":{"bwar":[["2026-06-30",-0.72]]},"savant_xstats_pitcher":{"ba":[["2026-06-30",0.277]],"bip":[["2026-06-30",136.0]],"era":[["2026-06-30",6.21]],"era_minus_xera_diff":[["2026-06-30",2.204]],"est_ba":[["2026-06-30",0.259]],"est_ba_minus_ba_diff":[["2026-06-30",0.018]],"est_slg":[["2026-06-30",0.406]],"est_slg_minus_slg_diff":[["2026-06-30",0.1059999999999999]],"est_woba":[["2026-06-30",0.312]],"est_woba_minus_woba_diff":[["2026-06-30",0.0449999999999999]],"pa":[["2026-06-30",180.0]],"slg":[["2026-06-30",0.512]],"woba":[["2026-06-30",0.357]],"xera":[["2026-06-30",4.01]]}}}