{"id":"678554","name":"Curtis Mead","team":null,"series":{"bref_war_batting":{"bwar":[["2026-06-30",1.03]]},"savant_oaa_fielder":{"fielding_runs_prevented":[["2026-06-30",-4.0]],"outs_above_average":[["2026-06-30",-6.0]],"outs_above_average_behind":[["2026-06-30",0.0]],"outs_above_average_infront":[["2026-06-30",0.0]],"outs_above_average_lateral_toward1bline":[["2026-06-30",0.0]],"outs_above_average_lateral_toward3bline":[["2026-06-30",-5.0]],"outs_above_average_lhh":[["2026-06-30",-7.0]],"outs_above_average_rhh":[["2026-06-30",1.0]]},"savant_xstats_batter":{"ba":[["2026-06-30",0.227]],"bip":[["2026-06-30",173.0]],"est_ba":[["2026-06-30",0.258]],"est_ba_minus_ba_diff":[["2026-06-30",-0.031]],"est_slg":[["2026-06-30",0.468]],"est_slg_minus_slg_diff":[["2026-06-30",0.0]],"est_woba":[["2026-06-30",0.358]],"est_woba_minus_woba_diff":[["2026-06-30",-0.012]],"pa":[["2026-06-30",251.0]],"slg":[["2026-06-30",0.468]],"woba":[["2026-06-30",0.346]]}}}